[
  {
    "complete": false,
    "name": "Master Sword",
    "locations": [
      "Unknown"
    ]
  },
  {
    "complete": false,
    "name": "Tree Branch",
    "locations": [
      "Hyrule Field",
      "West Necluda"
    ]
  },
  {
    "complete": false,
    "name": "Torch",
    "locations": [
      "Great Hyrule Field",
      "Hyrule Field"
    ]
  },
  {
    "complete": false,
    "name": "Soup Ladle",
    "locations": [
      "Hyrule Field",
      "Tabantha Frontier"
    ]
  },
  {
    "complete": false,
    "name": "Boomerang",
    "locations": [
      "West Necluda",
      "Faron Grasslands"
    ]
  },
  {
    "complete": false,
    "name": "Spring-Loaded Hammer",
    "locations": [
      "Kilton"
    ]
  },
  {
    "complete": false,
    "name": "Traveler's Sword",
    "locations": [
      "Hyrule Field",
      "West Necluda"
    ]
  },
  {
    "complete": false,
    "name": "Soldier's Broadsword",
    "locations": [
      "Hyrule Field",
      "Faron Grasslands"
    ]
  },
  {
    "complete": false,
    "name": "Knight's Broadsword",
    "locations": [
      "Gerudo Desert"
    ]
  },
  {
    "complete": false,
    "name": "Royal Broadsword",
    "locations": [
      "Tabantha Frontier",
      "Akkala Highlands"
    ]
  },
  {
    "complete": false,
    "name": "Forest Dweller's Sword",
    "locations": [
      "Great Hyrule Field",
      "Hyrule Field"
    ]
  },
  {
    "complete": false,
    "name": "Zora Sword",
    "locations": [
      "Lanayru Great Spring",
      "East Necluda"
    ]
  },
  {
    "complete": false,
    "name": "Feathered Edge",
    "locations": [
      "Tabantha Frontier",
      "Hyrule Field"
    ]
  },
  {
    "complete": false,
    "name": "Gerudo Scimitar",
    "locations": [
      "Gerudo Highlands",
      "Gerudo Desert"
    ]
  },
  {
    "complete": false,
    "name": "Moonlight Scimitar",
    "locations": [
      "Gerudo Highlands",
      "Gerudo Desert"
    ]
  },
  {
    "complete": false,
    "name": "Scimitar of the Seven",
    "locations": [
      "Gerudo Desert"
    ]
  },
  {
    "complete": false,
    "name": "Eightfold Blade",
    "locations": [
      "West Necluda",
      "Lake Hylia"
    ]
  },
  {
    "complete": false,
    "name": "Ancient Short Sword",
    "locations": [
      "Unknown"
    ]
  },
  {
    "complete": false,
    "name": "Rusty Broadsword",
    "locations": [
      "Hyule Field",
      "Eldin Canyon"
    ]
  },
  {
    "complete": false,
    "name": "Royal Guard's Sword",
    "locations": [
      "Hyrule Castle, Secret Room Above Armory"
    ]
  },
  {
    "complete": false,
    "name": "Flameblade",
    "locations": [
      "Hyrule Field",
      "East Necluda"
    ]
  },
  {
    "complete": false,
    "name": "Frostblade",
    "locations": [
      "Gerudo Highlands",
      "Hyrule Field"
    ]
  },
  {
    "complete": false,
    "name": "Thunderblade",
    "locations": [
      "Hyrule Field",
      "West Necluda"
    ]
  },
  {
    "complete": false,
    "name": "Boko Club",
    "locations": [
      "Hyrule Field",
      "West Necluda"
    ]
  },
  {
    "complete": false,
    "name": "Spiked Boko Club",
    "locations": [
      "Faron Grasslands",
      "East Necluda"
    ]
  },
  {
    "complete": false,
    "name": "Dragonbone Boko Club",
    "locations": [
      "Hyrule Ridge",
      "Necluda Sea"
    ]
  },
  {
    "complete": false,
    "name": "Lizal Boomerang",
    "locations": [
      "Lake Hylia",
      "Lanayru Wetlands"
    ]
  },
  {
    "complete": false,
    "name": "Lizal Forked Boomerang",
    "locations": [
      "Gerudo Desert",
      "Tabantha Frontier"
    ]
  },
  {
    "complete": false,
    "name": "Lizal Tri-Boomerang",
    "locations": [
      "Hebra Mountains",
      "Akkala Highlands"
    ]
  },
  {
    "complete": false,
    "name": "Guardian Sword",
    "locations": [
      "Eldin Canyon",
      "Tabantha Frontier"
    ]
  },
  {
    "complete": false,
    "name": "Guardian Sword+",
    "locations": [
      "Gerudo Highlands",
      "Akkala Highlands"
    ]
  },
  {
    "complete": false,
    "name": "Guardian Sword++",
    "locations": [
      "Hebra Mountains",
      "Akkala Highlands"
    ]
  },
  {
    "complete": false,
    "name": "Lynel Sword",
    "locations": [
      "Lanayru Great Spring",
      "Hyrule Field"
    ]
  },
  {
    "complete": false,
    "name": "Mighty Lynel Sword",
    "locations": [
      "Blue-Maned Lynel"
    ]
  },
  {
    "complete": false,
    "name": "Savage Lynel Sword",
    "locations": [
      "Hyrule Field",
      "Hebra Mountains"
    ]
  },
  {
    "complete": false,
    "name": "Fire Rod",
    "locations": [
      "Gerudo Highlands",
      "Great Hyrule Forest"
    ]
  },
  {
    "complete": false,
    "name": "Meteor Rod",
    "locations": [
      "Hyrule Field",
      "Hebra Mountains"
    ]
  },
  {
    "complete": false,
    "name": "Ice Rod",
    "locations": [
      "Gerudo Highlands",
      "Eldin Canyon"
    ]
  },
  {
    "complete": false,
    "name": "Blizzard Rod",
    "locations": [
      "Gerudo Highlands",
      "Hebra Mountains"
    ]
  },
  {
    "complete": false,
    "name": "Lightning Rod",
    "locations": [
      "West Necluda",
      "Hyrule Ridge"
    ]
  },
  {
    "complete": false,
    "name": "Thunder Rod",
    "locations": [
      "Hyrule Field",
      "Hyrule Ridge"
    ]
  },
  {
    "complete": false,
    "name": "Vicious Sickle",
    "locations": [
      "Gerudo Highlands",
      "Gerudo Desert"
    ]
  },
  {
    "complete": false,
    "name": "Demon Carver",
    "locations": [
      "Unknown"
    ]
  },
  {
    "complete": false,
    "name": "Bokoblin Arm",
    "locations": [
      "Greater Hyrule"
    ]
  },
  {
    "complete": false,
    "name": "Lizalfos Arm",
    "locations": [
      "Greater Hyrule"
    ]
  },
  {
    "complete": false,
    "name": "Korok Leaf",
    "locations": [
      "Hyrule Field",
      "West Necluda"
    ]
  },
  {
    "complete": false,
    "name": "Farming Hoe",
    "locations": [
      "East Necluda",
      "Hyrule Field"
    ]
  },
  {
    "complete": false,
    "name": "Boat Oar",
    "locations": [
      "East Necluda",
      "Necluda Sea"
    ]
  },
  {
    "complete": false,
    "name": "Woodcutter's Axe",
    "locations": [
      "West Necluda",
      "Hyrule Field"
    ]
  },
  {
    "complete": false,
    "name": "Double Axe",
    "locations": [
      "West Necluda",
      "Gerudo Highlands"
    ]
  },
  {
    "complete": false,
    "name": "Iron Sledgehammer",
    "locations": [
      "Eldin Canyon",
      "Akkala Highlands"
    ]
  },
  {
    "complete": false,
    "name": "Giant Boomerang",
    "locations": [
      "West Necluda",
      "Hebra Mountains"
    ]
  },
  {
    "complete": false,
    "name": "Traveler's Claymore",
    "locations": [
      "Hyrule Field",
      "West Necluda"
    ]
  },
  {
    "complete": false,
    "name": "Soldier's Claymore",
    "locations": [
      "Hyrule Field",
      "Faron Grasslands"
    ]
  },
  {
    "complete": false,
    "name": "Knight's Claymore",
    "locations": [
      "Gerudo Desert",
      "Tabantha Frontier"
    ]
  },
  {
    "complete": false,
    "name": "Royal Claymore",
    "locations": [
      "Tabantha Frontier",
      "Gerudo Desert"
    ]
  },
  {
    "complete": false,
    "name": "Silver Longsword",
    "locations": [
      "Lanayru Great Spring",
      "Lanayru Wetlands"
    ]
  },
  {
    "complete": false,
    "name": "Cobble Crusher",
    "locations": [
      "Eldin Canyon",
      "Eldin Mountains"
    ]
  },
  {
    "complete": false,
    "name": "Stone Smasher",
    "locations": [
      "Eldin Canyon Hyrule Field"
    ]
  },
  {
    "complete": false,
    "name": "Boulder Breaker",
    "locations": [
      "Eldin Mountains"
    ]
  },
  {
    "complete": false,
    "name": "Golden Claymore",
    "locations": [
      "Gerudo Highlands",
      "Hyrule Ridge"
    ]
  },
  {
    "complete": false,
    "name": "Eightfold Longblade",
    "locations": [
      "West Necluda",
      "Lanaryu Great Spring"
    ]
  },
  {
    "complete": false,
    "name": "Edge of Duality",
    "locations": [
      "Hyrule Field",
      "West Necluda"
    ]
  },
  {
    "complete": false,
    "name": "Ancient Bladesaw",
    "locations": [
      "Unknown"
    ]
  },
  {
    "complete": false,
    "name": "Rusty Claymore",
    "locations": [
      "Hyrule Field",
      "Eldin Canyon"
    ]
  },
  {
    "complete": false,
    "name": "Royal Guard's Claymore",
    "locations": [
      "Unknown"
    ]
  },
  {
    "complete": false,
    "name": "Great Flameblade",
    "locations": [
      "Hyrule Field",
      "Eldin Canyon"
    ]
  },
  {
    "complete": false,
    "name": "Great Frostblade",
    "locations": [
      "Hebra Mountains",
      "Hyrule Field"
    ]
  },
  {
    "complete": false,
    "name": "Great Thunderblade",
    "locations": [
      "Hyrule Field",
      "Tabantha Frontier"
    ]
  },
  {
    "complete": false,
    "name": "Boko Bat",
    "locations": [
      "Hyrule Field",
      "West Necluda"
    ]
  },
  {
    "complete": false,
    "name": "Spiked Boko Bat",
    "locations": [
      "Faron Grasslands",
      "East Necluda"
    ]
  },
  {
    "complete": false,
    "name": "Dragonbone Boko Bat",
    "locations": [
      "Hyrule Ridge",
      "Necluda Sea"
    ]
  },
  {
    "complete": false,
    "name": "Moblin Club",
    "locations": [
      "Gerudo Highlands",
      "Faron Grasslands"
    ]
  },
  {
    "complete": false,
    "name": "Spiked Moblin Club",
    "locations": [
      "Hyrule Field",
      "Akkala Highlands"
    ]
  },
  {
    "complete": false,
    "name": "Dragonbone Moblin Club",
    "locations": [
      "Hebra Mountains",
      "Eldin Mountains"
    ]
  },
  {
    "complete": false,
    "name": "Ancient Battle Axe",
    "locations": [
      "Gerudo Desert",
      "Hyrule Field"
    ]
  },
  {
    "complete": false,
    "name": "Ancient Battle Axe+",
    "locations": [
      "Akkala Highlands",
      "Hyrule Field"
    ]
  },
  {
    "complete": false,
    "name": "Ancient Battle Axe++",
    "locations": [
      "Hebra Mountains",
      "Gerudo Highlands"
    ]
  },
  {
    "complete": false,
    "name": "Lynel Crusher",
    "locations": [
      "Lynel"
    ]
  },
  {
    "complete": false,
    "name": "Mighty Lynel Crusher",
    "locations": [
      "Blue-Maned Lynel"
    ]
  },
  {
    "complete": false,
    "name": "Savage Lynel Crusher",
    "locations": [
      "Hebra Mountains",
      "Eldin Mountains"
    ]
  },
  {
    "complete": false,
    "name": "Windcleaver",
    "locations": [
      "Gerudo Highlands",
      "West Necluda"
    ]
  },
  {
    "complete": false,
    "name": "Moblin Arm",
    "locations": [
      "Greater Hyrule"
    ]
  },
  {
    "complete": false,
    "name": "Wooden Mop",
    "locations": [
      "East Necluda Hyrule Field"
    ]
  },
  {
    "complete": false,
    "name": "Farmer's Pitchfork",
    "locations": [
      "East Necluda",
      "West Necluda"
    ]
  },
  {
    "complete": false,
    "name": "Fishing Harpoon",
    "locations": [
      "East Necluda",
      "Lake Hylia"
    ]
  },
  {
    "complete": false,
    "name": "Throwing Spear",
    "locations": [
      "West Necluda",
      "Hyrule Field"
    ]
  },
  {
    "complete": false,
    "name": "Traveler's Spear",
    "locations": [
      "Hyrule Field",
      "West Necluda"
    ]
  },
  {
    "complete": false,
    "name": "Soldier's Spear",
    "locations": [
      "Hyrule Field",
      "Faron Grasslands"
    ]
  },
  {
    "complete": false,
    "name": "Knight's Halberd",
    "locations": [
      "Tabantha Frontier",
      "Gerudo Desert"
    ]
  },
  {
    "complete": false,
    "name": "Royal Halberd",
    "locations": [
      "Gerudo Highands",
      "Tabantha Frontier"
    ]
  },
  {
    "complete": false,
    "name": "Forest Dweller's Spear",
    "locations": [
      "Great Hyrule Forest",
      "Hyrule Ridge"
    ]
  },
  {
    "complete": false,
    "name": "Zora Spear",
    "locations": [
      "Lanayru Great Spring",
      "Lake Hylia"
    ]
  },
  {
    "complete": false,
    "name": "Silverscale Spear",
    "locations": [
      "Akkala Highlands",
      "Lanayru Great Spring"
    ]
  },
  {
    "complete": false,
    "name": "Ceremonial Trident",
    "locations": [
      "Lanayru Great Spring"
    ]
  },
  {
    "complete": false,
    "name": "Lightscale Trident",
    "locations": [
      "Lanayru Great Spring"
    ]
  },
  {
    "complete": false,
    "name": "Drillshaft",
    "locations": [
      "Eldin Canyon",
      "Hebra Mountains"
    ]
  },
  {
    "complete": false,
    "name": "Feathered Spear",
    "locations": [
      "Tabantha Frontier",
      "Hyrule Field"
    ]
  },
  {
    "complete": false,
    "name": "Gerudo Spear",
    "locations": [
      "Gerudo Highlands",
      "Gerudo Desert"
    ]
  },
  {
    "complete": false,
    "name": "Serpentine Spear",
    "locations": [
      "East Necluda",
      "Hyrule Field"
    ]
  },
  {
    "complete": false,
    "name": "Ancient Spear",
    "locations": [
      "Unknown"
    ]
  },
  {
    "complete": false,
    "name": "Rusty Halberd",
    "locations": [
      "Hyrule Field",
      "Great Hyrule Forest"
    ]
  },
  {
    "complete": false,
    "name": "Royal Guard's Spear",
    "locations": [
      "Hyrule Castle, Dining Hall"
    ]
  },
  {
    "complete": false,
    "name": "Flamespear",
    "locations": [
      "Hyrule Field",
      "Hebra Mountains"
    ]
  },
  {
    "complete": false,
    "name": "Frostspear",
    "locations": [
      "Hebra Mountais",
      "Hyrule Field"
    ]
  },
  {
    "complete": false,
    "name": "Thunderspear",
    "locations": [
      "Hyrule Ridge",
      "Hyrule Field"
    ]
  },
  {
    "complete": false,
    "name": "Boko Spear",
    "locations": [
      "West Necluda",
      "Hyrule Field"
    ]
  },
  {
    "complete": false,
    "name": "Spiked Boko Spear",
    "locations": [
      "Faron Grasslands",
      "East Necluda"
    ]
  },
  {
    "complete": false,
    "name": "Dragonbone Boko Spear",
    "locations": [
      "Necluda Sea",
      "Hyrule Ridge"
    ]
  },
  {
    "complete": false,
    "name": "Moblin Spear",
    "locations": [
      "Faron Grasslands",
      "Gerudo Highlands"
    ]
  },
  {
    "complete": false,
    "name": "Spiked Moblin Spear",
    "locations": [
      "Gerudo Highlands",
      "Akkala Highlands"
    ]
  },
  {
    "complete": false,
    "name": "Dragonbone Moblin Spear",
    "locations": [
      "Hebra Mountains",
      "Eldin Mountains"
    ]
  },
  {
    "complete": false,
    "name": "Lizal Spear",
    "locations": [
      "Lanaryu Wetlands",
      "East Necluda"
    ]
  },
  {
    "complete": false,
    "name": "Enhanced Lizal Spear",
    "locations": [
      "Tabantha Frontier",
      "Gerudo Desert"
    ]
  },
  {
    "complete": false,
    "name": "Forked Lizal Spear",
    "locations": [
      "Eldin Canyon",
      "Akkala Highlands"
    ]
  },
  {
    "complete": false,
    "name": "Guardian Spear",
    "locations": [
      "Hyrule Field",
      "Hebra Mountains"
    ]
  },
  {
    "complete": false,
    "name": "Guardian Spear+",
    "locations": [
      "Gerudo Highlands",
      "Hyrule Field"
    ]
  },
  {
    "complete": false,
    "name": "Guardian Spear++",
    "locations": [
      "Hebra Mountains",
      "Akkala Highlands"
    ]
  },
  {
    "complete": false,
    "name": "Lynel Spear",
    "locations": [
      "Lynel"
    ]
  },
  {
    "complete": false,
    "name": "Mighty Lynel Spear",
    "locations": [
      "Blue-Maned Lynel"
    ]
  },
  {
    "complete": false,
    "name": "Savage Lynel Spear",
    "locations": [
      "White-Maned Lynel"
    ]
  },
  {
    "complete": false,
    "name": "Bow of Light",
    "locations": [
      "Unknown"
    ]
  },
  {
    "complete": false,
    "name": "Wooden Bow",
    "locations": [
      "Hyrule Field",
      "West Necluda"
    ]
  },
  {
    "complete": false,
    "name": "Traveler's Bow",
    "locations": [
      "Hyrule Field",
      "West Necluda"
    ]
  },
  {
    "complete": false,
    "name": "Soldier's Bow",
    "locations": [
      "Hyrule Field",
      "Faron Grasslands"
    ]
  },
  {
    "complete": false,
    "name": "Knight's Bow",
    "locations": [
      "Gerudo Desert",
      "Tabantha Frontier"
    ]
  },
  {
    "complete": false,
    "name": "Royal Bow",
    "locations": [
      "Tabantha Frontier Hebra Mountains"
    ]
  },
  {
    "complete": false,
    "name": "Forest Dweller's Bow",
    "locations": [
      "Tabantha Froniter",
      "Hyrule Ridge"
    ]
  },
  {
    "complete": false,
    "name": "Silver Bow",
    "locations": [
      "Lanaryu Great Spring",
      "Akkala Highlands"
    ]
  },
  {
    "complete": false,
    "name": "Swallow Bow",
    "locations": [
      "Tabantha Froniter",
      "Hebra Mountains"
    ]
  },
  {
    "complete": false,
    "name": "Falcon Bow",
    "locations": [
      "Tabantha Frontier",
      "Hebra Mountains"
    ]
  },
  {
    "complete": false,
    "name": "Great Eagle Bow",
    "locations": [
      "Tabantha Frontier"
    ]
  },
  {
    "complete": false,
    "name": "Golden Bow",
    "locations": [
      "Gerudo Highlands",
      "Gerudo Desert"
    ]
  },
  {
    "complete": false,
    "name": "Phrenic Bow",
    "locations": [
      "West Necluda",
      "Lake Hylia"
    ]
  },
  {
    "complete": false,
    "name": "Ancient Bow",
    "locations": [
      "Unknown"
    ]
  },
  {
    "complete": false,
    "name": "Royal Guard's Bow",
    "locations": [
      "Hyrule Castle, Zelda's Chambers"
    ]
  },
  {
    "complete": false,
    "name": "Boko Bow",
    "locations": [
      "Hyrule Field",
      "West Necluda"
    ]
  },
  {
    "complete": false,
    "name": "Spiked Boko Bow",
    "locations": [
      "Faron Grasslands",
      "East Necluda"
    ]
  },
  {
    "complete": false,
    "name": "Dragonbone Boko Bow",
    "locations": [
      "Hyrule Ridge",
      "Hyrule Field"
    ]
  },
  {
    "complete": false,
    "name": "Lizal Bow",
    "locations": [
      "Lanayru Great Spring",
      "Lanaryu Wetlands"
    ]
  },
  {
    "complete": false,
    "name": "Strengthened Lizal Bow",
    "locations": [
      "Tabantha Frontier",
      "Gerudo Desert"
    ]
  },
  {
    "complete": false,
    "name": "Steel Lizal Bow",
    "locations": [
      "Hebra Mountains",
      "Akkala Highlands"
    ]
  },
  {
    "complete": false,
    "name": "Lynel Bow",
    "locations": [
      "Gerudo Highlands",
      "Lanaryu Great Spring",
      "Lynel"
    ]
  },
  {
    "complete": false,
    "name": "Mighty Lynel Bow",
    "locations": [
      "Hyrule Field",
      "Deep Akkala",
      "Blue-Maned Lynel"
    ]
  },
  {
    "complete": false,
    "name": "Savage Lynel Bow",
    "locations": [
      "Hebra Mountains",
      "Hyrule Field",
      "White-Maned Lynel"
    ]
  },
  {
    "complete": false,
    "name": "Duplex Bow",
    "locations": [
      "Gerudo Highlands"
    ]
  },
  {
    "complete": false,
    "name": "Arrow",
    "locations": [
      "Hyrule Field",
      "Eldin Canyon"
    ]
  },
  {
    "complete": false,
    "name": "Fire Arrow",
    "locations": [
      "Hyrule Field",
      "Eldin Canyon"
    ]
  },
  {
    "complete": false,
    "name": "Ice Arrow",
    "locations": [
      "Hyrule Field",
      "Hebra Mountains"
    ]
  },
  {
    "complete": false,
    "name": "Shock Arrow",
    "locations": [
      "Lanayru Great Spring",
      "Hyrule Field"
    ]
  },
  {
    "complete": false,
    "name": "Bomb Arrow",
    "locations": [
      "Hyrule Field",
      "East Necluda"
    ]
  },
  {
    "complete": false,
    "name": "Ancient Arrow",
    "locations": [
      "Hyrule Field"
    ]
  },
  {
    "complete": false,
    "name": "Hylian Shield",
    "locations": [
      "Hyrule Castle, Lockup (Chest)"
    ]
  },
  {
    "complete": false,
    "name": "Pot Lid",
    "locations": [
      "Hyrule Field",
      "East Necluda"
    ]
  },
  {
    "complete": false,
    "name": "Wooden Shield",
    "locations": [
      "Hyrule Field",
      "East Necluda"
    ]
  },
  {
    "complete": false,
    "name": "Emblazoned Shield",
    "locations": [
      "East Necluda",
      "Hebra Mountains"
    ]
  },
  {
    "complete": false,
    "name": "Hunter's Shield",
    "locations": [
      "Hebra Mountains",
      "Lanaryu Wetlands"
    ]
  },
  {
    "complete": false,
    "name": "Fisherman's Shield",
    "locations": [
      "East Necluda",
      "Hebra Mountains"
    ]
  },
  {
    "complete": false,
    "name": "Traveler's Shield",
    "locations": [
      "Hyrule Field",
      "West Necluda"
    ]
  },
  {
    "complete": false,
    "name": "Soldier's Shield",
    "locations": [
      "Tabantha Frontier",
      "Hyrule Field."
    ]
  },
  {
    "complete": false,
    "name": "Knight's Shield",
    "locations": [
      "Hebra Mountains",
      "Eldin Mountains"
    ]
  },
  {
    "complete": false,
    "name": "Royal Shield",
    "locations": [
      "Hyrule Field",
      "Hebra Mountains"
    ]
  },
  {
    "complete": false,
    "name": "Forest Dweller's Shield",
    "locations": [
      "Great Hyrule Forest"
    ]
  },
  {
    "complete": false,
    "name": "Silver Shield",
    "locations": [
      "Lanayru Great Spring",
      "Lake Hylia"
    ]
  },
  {
    "complete": false,
    "name": "Kite Shield",
    "locations": [
      "Hebra Mountains",
      "Tabantha Frontier"
    ]
  },
  {
    "complete": false,
    "name": "Gerudo Shield",
    "locations": [
      "Gerudo Highlands",
      "Gerudo Desert"
    ]
  },
  {
    "complete": false,
    "name": "Radiant Shield",
    "locations": [
      "Gerudo Highlands",
      "Gerudo Desert"
    ]
  },
  {
    "complete": false,
    "name": "Daybreaker",
    "locations": [
      "Gerudo Desert"
    ]
  },
  {
    "complete": false,
    "name": "Shield of the Mind's Eye",
    "locations": [
      "West Necluda",
      "East Necluda"
    ]
  },
  {
    "complete": false,
    "name": "Ancient Shield",
    "locations": [
      "Unknown"
    ]
  },
  {
    "complete": false,
    "name": "Rusty Shield",
    "locations": [
      "Hyrule Field",
      "East Necluda"
    ]
  },
  {
    "complete": false,
    "name": "Royal Guard's Shield",
    "locations": [
      "Hyrule Castle, Library King's Study"
    ]
  },
  {
    "complete": false,
    "name": "Boko Shield",
    "locations": [
      "Hyrule Field",
      "West Necluda"
    ]
  },
  {
    "complete": false,
    "name": "Spiked Boko Shield",
    "locations": [
      "Faron Grasslands",
      "East Necluda"
    ]
  },
  {
    "complete": false,
    "name": "Dragonbone Boko Shield",
    "locations": [
      "Hyrule Ridge",
      "Necluda Sea"
    ]
  },
  {
    "complete": false,
    "name": "Lizal Shield",
    "locations": [
      "Lake Hylia",
      "East Necluda"
    ]
  },
  {
    "complete": false,
    "name": "Reinforced Lizal Shield",
    "locations": [
      "Tabantha Frontier",
      "Gerudo Desert"
    ]
  },
  {
    "complete": false,
    "name": "Steel Lizal Shield",
    "locations": [
      "Hebra Mountains",
      "Akkala Highlands"
    ]
  },
  {
    "complete": false,
    "name": "Guardian Shield",
    "locations": [
      "West Necluda",
      "Lanayru Great Spring"
    ]
  },
  {
    "complete": false,
    "name": "Guardian Shield+",
    "locations": [
      "East Necluda",
      "Faron Grasslands"
    ]
  },
  {
    "complete": false,
    "name": "Guardian Shield++",
    "locations": [
      "Gerudo Highlands",
      "Akkala Highlands"
    ]
  },
  {
    "complete": false,
    "name": "Lynel Shield",
    "locations": [
      "Lanayru Great Spring",
      "Hyrule Field"
    ]
  },
  {
    "complete": false,
    "name": "Mighty Lynel Shield",
    "locations": [
      "Hyrule Field",
      "Lanaryu Great Spring"
    ]
  },
  {
    "complete": false,
    "name": "Savage Lynel Shield",
    "locations": [
      "Hyrule Field",
      "Hebra Mountains"
    ]
  }
]
